vbimage/.DS_Store
vbimage/__init__.py
vbimage/__main__.py
vbimage/blur.py
vbimage/contrast.py
vbimage/gradient.py
vbimage/grid.py
vbimage/info.py
vbimage/layer.py
vbimage/main.py
vbimage/pixelate.py
vbimage/removebg.py
vbimage/render.py
vbimage/resize.py
vbimage/stack.py
vbimage/temp/main.log
vbimage/temp/main.tex
vbimage/temp/texput.log
vbimage-0.1.43.dist-info/METADATA
vbimage-0.1.43.dist-info/WHEEL
vbimage-0.1.43.dist-info/entry_points.txt
vbimage-0.1.43.dist-info/RECORD
