Metadata-Version: 2.1
Name: vbimage
Version: 0.1.43
Summary: Added contrast to increase the contrast of the image
Author: vaibhavblayer
Author-email: vaibhavblayer@gmail.com
Requires-Python: >=3.12,<4.0
Classifier: Programming Language :: Python :: 3
Classifier: Programming Language :: Python :: 3.12
Requires-Dist: click (>=8.1.3,<9.0.0)
Requires-Dist: pillow (>=10.3.0,<11.0.0)
